classification_library/__init__.cpython-38-x86_64-linux-gnu.so
classification_library-0.0.3.dist-info/METADATA
classification_library-0.0.3.dist-info/top_level.txt
classification_library-0.0.3.dist-info/WHEEL
classification_library-0.0.3.dist-info/RECORD
