Metadata-Version: 2.1
Name: classification-library
Version: 0.0.3
Summary: A classification library using a novel audio-inspired algorithm.
Home-page: https://github.com/lol-cubes/classification-library
Author: Arin Khare
License: UNKNOWN
Platform: UNKNOWN
Requires-Dist: numpy (>=1.19.2)
Requires-Dist: playsound (==1.2.2)
Requires-Dist: PyObjC ; platform_system == "Darwin"
Requires-Dist: PyGObject ; platform_system == "Linux"
